README
setup.py
izaber_plpython/__init__.py
izaber_plpython/base.py
izaber_plpython.egg-info/PKG-INFO
izaber_plpython.egg-info/SOURCES.txt
izaber_plpython.egg-info/dependency_links.txt
izaber_plpython.egg-info/not-zip-safe
izaber_plpython.egg-info/requires.txt
izaber_plpython.egg-info/top_level.txt