Metadata-Version: 1.1
Name: izaber-plpython
Version: 1.0
Summary: Base load point for iZaber plpython
Home-page: https://github.com/zabertech/izaber-plpython
Author: Aki Mimoto
Author-email: aki+izaber@zaber.com
License: MIT
Download-URL: https://github.com/zabertech/python-plpython/archive/1.0.tar.gz
Platform: UNKNOWN
